<?xml version="1.0" encoding="UTF-8"?>
<!--
        Attention: Generated code! Do not modify by hand!
        Generated by: hibernate.hbm.xml.vsl in andromda-hibernate-cartridge.
     -->
<!DOCTYPE hibernate-mapping PUBLIC "-//Hibernate/Hibernate Mapping DTD 3.0//EN"
    "http://www.hibernate.org/dtd/hibernate-mapping-3.0.dtd">

<hibernate-mapping default-cascade="none">
   <class name="ubic.gemma.model.common.auditAndSecurity.acl.AclObjectIdentity" table="ACLOBJECTIDENTITY" dynamic-insert="false" dynamic-update="false">
      <cache usage="read-write" />
      <id name="id" type="java.lang.Long" unsaved-value="null">
         <column name="ID" sql-type="BIGINT"/>
         <generator class="native">
         </generator>
      </id>
      <property name="identifier" type="java.lang.Long">
         <column name="OBJECT_ID" not-null="true" unique="false" sql-type="BIGINT"/>
      </property>
      <property name="type" type="java.lang.String">
         <column name="OBJECT_CLASS" not-null="true" unique="false" sql-type="VARCHAR(255) character set latin1 collate latin1_swedish_ci" />
      </property>
      <property name="entriesInheriting" type="java.lang.Boolean">
         <column name="ENTRIES_INHERITING" not-null="true" unique="false" sql-type="TINYINT"/>
      </property>
      <many-to-one name="ownerSid" class="ubic.gemma.model.common.auditAndSecurity.acl.AclSid"  lazy="false" fetch="select">
         <column name="OWNER_SID_FK" not-null="true" sql-type="BIGINT"/>
      </many-to-one> 
      <many-to-one name="parentObject" class="ubic.gemma.model.common.auditAndSecurity.acl.AclObjectIdentity"  lazy="false" fetch="select">
         <column name="PARENT_OBJECT_FK" not-null="false" sql-type="BIGINT"/>
      </many-to-one>
      <set name="entries" lazy="false" fetch="join" inverse="false" cascade="all"  order-by="ACE_ORDER">
         <cache usage="read-write" />
         <key foreign-key="ACL_ENTRY_OBJECTIDENTITY_FKC">
            <column name="OBJECTIDENTITY_FK" sql-type="BIGINT"/>
         </key>
         <one-to-many class="ubic.gemma.model.common.auditAndSecurity.acl.AclEntry" /> 
      </set>
   </class>
</hibernate-mapping>
