<?xml version="1.0" encoding="UTF-8"?>
<!-- Attention: Generated code! Do not modify by hand! Generated by: hibernate.hbm.xml.vsl in andromda-hibernate-cartridge. -->
<!DOCTYPE hibernate-mapping PUBLIC "-//Hibernate/Hibernate Mapping DTD 3.0//EN"
          "http://www.hibernate.org/dtd/hibernate-mapping-3.0.dtd">

<hibernate-mapping default-cascade="none">
	<class name="ubic.gemma.model.association.coexpression.MouseProbeCoExpressionImpl" table="MOUSE_PROBE_CO_EXPRESSION"
		dynamic-insert="false" dynamic-update="false" mutable="false">
		<cache usage="read-write" />
		<id access="field" name="id" type="java.lang.Long" unsaved-value="null">
			<column name="ID" sql-type="BIGINT" />
			<generator class="native">
			</generator>
		</id>
		<property access="field" name="score" type="java.lang.Double">
			<column name="SCORE" not-null="true" unique="false" sql-type="DOUBLE" />
		</property>

		<many-to-one access="field" name="expressionBioAssaySet" class="ubic.gemma.model.expression.experiment.BioAssaySet"
			lazy="proxy" fetch="select">
			<column name="EXPRESSION_EXPERIMENT_FK" not-null="true" sql-type="BIGINT" />
		</many-to-one>
		<many-to-one access="field" name="secondVector"
			class="ubic.gemma.model.expression.bioAssayData.ProcessedExpressionDataVectorImpl" lazy="proxy" fetch="select">
			<column name="SECOND_VECTOR_FK" not-null="true" sql-type="BIGINT" />
		</many-to-one>
		<many-to-one access="field" name="firstVector"
			class="ubic.gemma.model.expression.bioAssayData.ProcessedExpressionDataVectorImpl" lazy="proxy" fetch="select">
			<column name="FIRST_VECTOR_FK" not-null="true" sql-type="BIGINT" />
		</many-to-one>
		<many-to-one access="field" name="sourceAnalysis" class="ubic.gemma.model.analysis.Analysis" lazy="proxy"
			fetch="select">
			<column name="SOURCE_ANALYSIS_FK" not-null="false" sql-type="BIGINT" />
		</many-to-one>
	</class>
</hibernate-mapping>